pii_redactor/__init__.py
pii_redactor/pii_redactor.py
pii_redactor/tests/__init__.py
pii_redactor/tests/conftest.py
pii_redactor/tests/test_file_handler.py
pii_redactor/tests/test_redactor.py
pii_redactor-0.1.dist-info/LICENSE
pii_redactor-0.1.dist-info/METADATA
pii_redactor-0.1.dist-info/WHEEL
pii_redactor-0.1.dist-info/entry_points.txt
pii_redactor-0.1.dist-info/top_level.txt
pii_redactor-0.1.dist-info/RECORD
