Metadata-Version: 2.2
Name: pii_redactor
Version: 0.1
Summary: Advanced PII detection and redaction library
Home-page: https://github.com/your-username/pii-redactor
Author: Uwakwe, Ikechukwu Henry
Author-email: henry.uwakxy@gmail.com
Classifier: Programming Language :: Python :: 3
Classifier: License :: OSI Approved :: MIT License
Classifier: Operating System :: OS Independent
Requires-Python: >=3.8
License-File: LICENSE
Requires-Dist: spacy>=3.0
Requires-Dist: python-docx>=0.8.11
Requires-Dist: pdfplumber>=0.6.0
Requires-Dist: phonenumbers>=8.12.0
Requires-Dist: luhn
Requires-Dist: pyyaml>=5.0
